rtsf_win-1.2.1.dist-info/METADATA
rtsf_win-1.2.1.dist-info/RECORD
rtsf_win-1.2.1.dist-info/WHEEL
rtsf_win-1.2.1.dist-info/entry_points.txt
rtsf_win-1.2.1.dist-info/top_level.txt
winuidriver/__about__.py
winuidriver/__init__.py
winuidriver/actions.py
winuidriver/cli.py
winuidriver/driver.py
