Metadata-Version: 2.1
Name: rtsf-win
Version: 1.2.1
Summary: only for windows UI test, base on rtsf. e.g. WPF UI or MFC UI
Home-page: https://github.com/RockFeng0/rtsf-win
Author: 罗科峰
Author-email: lkf20031988@163.com
License: MIT
Keywords: test win ui
Platform: UNKNOWN
Requires-Python: >=2.7, !=3.0.*, !=3.1.*, !=3.2.*, !=3.3.*, <4
Requires-Dist: uiautomation
Requires-Dist: rtsf
